{
  "artifactKind": "metrics",
  "branch": "codex/closeout-ledger-schema-convergence",
  "committedDeltaPathCount": 1,
  "createdAt": "2026-05-06T22:45:00+00:00",
  "detectorHash": "d6cf4d2a23c73d53c7e826d87991c70b",
  "dirtyCounts": {
    "foreignDirty": 0,
    "mixedDirty": 0,
    "ownedDirty": 0,
    "unownedDirty": 0
  },
  "featureHead": "dff8f6659f47ca0110425d2715377caeeec9cf0d",
  "schemaVersion": "1.0",
  "targetHead": "f7aebd5447bd3ef69daec14448d516805cedbd77",
  "workBlockId": "wb-5a6943f02baf4334"
}
